Metadata-Version: 2.1
Name: django-safe-filefield-new
Version: 0.4.1
Summary: Secure file field, which allows you to restrict uploaded file extensions.
Home-page: https://github.com/beckedorf/django-safe-filefield-new
Author: Vladislav Bakin
Author-email: mixkorshun@gmail.com
Maintainer: Janis Beckedorf
Maintainer-email: mail@janisbeckedorf.de
License: MIT
Keywords: django,filefield,model-field,form-field
Platform: UNKNOWN
Classifier: Development Status :: 4 - Beta
Classifier: Intended Audience :: Developers
Classifier: Environment :: Web Environment
Classifier: Framework :: Django
Classifier: Topic :: Security
Classifier: Natural Language :: English
Classifier: License :: OSI Approved :: MIT License
Classifier: Programming Language :: Python
Classifier: Programming Language :: Python :: 3
Classifier: Programming Language :: Python :: 3.6
Classifier: Programming Language :: Python :: 3.7
Classifier: Programming Language :: Python :: 3.8
Classifier: Programming Language :: Python :: 3.9
Requires-Dist: django
Requires-Dist: python-magic
Requires-Dist: clamd
